pi_gpio_api/__init__.py
pi_gpio_api/__main__.py
pi_gpio_api/core/GPIO_mock.py
pi_gpio_api/core/__init__.py
pi_gpio_api/core/app.py
pi_gpio_api/core/pi.py
pi_gpio_api/core/pin_layout.py
pi_gpio_api-0.1.1.dist-info/LICENSE
pi_gpio_api-0.1.1.dist-info/METADATA
pi_gpio_api-0.1.1.dist-info/WHEEL
pi_gpio_api-0.1.1.dist-info/entry_points.txt
pi_gpio_api-0.1.1.dist-info/top_level.txt
pi_gpio_api-0.1.1.dist-info/RECORD
