Metadata-Version: 2.1
Name: pi-gpio-api
Version: 0.1.1
Summary: web API to control Raspberry Pi GPIO
Home-page: https://github.com/jcapona/pi-gpio-api
Author: Jorge Capona
Author-email: jcapona@gmail.com
License: MIT
Keywords: raspberry pi api gpio io
Platform: UNKNOWN
Classifier: Development Status :: 3 - Alpha
Classifier: Intended Audience :: Developers
Classifier: Topic :: Software Development
Classifier: Topic :: Software Development :: Embedded Systems
Classifier: Topic :: System
Classifier: License :: OSI Approved :: MIT License
Classifier: Programming Language :: Python :: 3.6
Requires-Dist: click (==6.7)
Requires-Dist: daemonocle (==1.0.1)
Requires-Dist: docutils (==0.15.2)
Requires-Dist: Flask (==0.12.2)
Requires-Dist: itsdangerous (==0.24)
Requires-Dist: Jinja2 (==2.9.6)
Requires-Dist: lockfile (==0.12.2)
Requires-Dist: MarkupSafe (==1.0)
Requires-Dist: pigpio (==1.35)
Requires-Dist: psutil (==5.6.3)
Requires-Dist: RPi.GPIO (==0.7.0)
Requires-Dist: Werkzeug (==0.12.2)
